nbawebstats.py
nbawebstats/requests.json
nbawebstats-0.1.2.dist-info/top_level.txt
nbawebstats-0.1.2.dist-info/METADATA
nbawebstats-0.1.2.dist-info/RECORD
nbawebstats-0.1.2.dist-info/metadata.json
nbawebstats-0.1.2.dist-info/DESCRIPTION.rst
nbawebstats-0.1.2.dist-info/WHEEL
