Metadata-Version: 2.0
Name: nbawebstats
Version: 0.1.2
Summary: Python interface to stats.nba.com HTTP API.
Home-page: https://github.com/agirardeaudale/nbawebstats
Author: Andrew Girardeau-Dale
Author-email: agirardeaudale@gmail.com
License: MIT
Download-URL: https://github.com/agirardeaudale/nbawebstats/tarball/v0.1.2
Keywords: nbawebstats
Platform: UNKNOWN
Classifier: Development Status :: 2 - Pre-Alpha
Classifier: Intended Audience :: Developers
Classifier: License :: OSI Approved :: MIT License
Classifier: Natural Language :: English
Classifier: Programming Language :: Python :: 2
Classifier: Programming Language :: Python :: 2.6
Classifier: Programming Language :: Python :: 2.7
Classifier: Programming Language :: Python :: 3
Classifier: Programming Language :: Python :: 3.3
Classifier: Programming Language :: Python :: 3.4
Classifier: Programming Language :: Python :: 3.5
Requires-Dist: requests
